TPLinkController/__init__.py
TPLinkController/controller.py
TPLinkController/controller_old.py
tp_link_controller-0.0.2.dist-info/LICENSE
tp_link_controller-0.0.2.dist-info/METADATA
tp_link_controller-0.0.2.dist-info/WHEEL
tp_link_controller-0.0.2.dist-info/top_level.txt
tp_link_controller-0.0.2.dist-info/RECORD
