Metadata-Version: 2.1
Name: tp-link-controller
Version: 0.0.2
Summary: A Python Package to controll TP-Link Routers
Home-page: https://github.com/fazalfarhan01/TP-Link-Router-Controller
Author: Mohamed Farhan Fazal
Author-email: fazal.farhan@gmail.com
License: UNKNOWN
Platform: UNKNOWN
Classifier: Programming Language :: Python :: 3
Classifier: License :: OSI Approved :: GNU Affero General Public License v3
Classifier: Operating System :: OS Independent
Requires-Python: >=3.6
Requires-Dist: colorama
Requires-Dist: selenium
Requires-Dist: browsermob-proxy
